{
    "intent": 0.4595496356487274,
    "directness_of_causality": 0.05118532478809357,
    "injured_count": 0.13335172832012177,
    "treating": 0.13907988369464874,
    "HRA Strategy.time-resources.take-the-best": 0.00827313307672739,
    "HRA Strategy.resources-system.take-the-best": 0.01346050575375557,
    "HRA Strategy.risk_reward_ratio-system.one-bounce": 0.0006455862894654274,
    "HRA Strategy.time-resources-system.tallying": 0.0005847053835168481,
    "AVERAGE_TIME_USED": 0.0011866023996844888,
    "SUPPLIES_USED": 0.19268293678760529
}